{
    "eeeeeeww|East": -13.64665477603967,
    "eeeeeeww|South": -1.6633359017627607,
    "eeeeeeww|Stop": -1.6527523535150122,
    "eeeeeeww|West": -10.573554150635228,
    "eeeeewww|East": -110.10467319075252,
    "eeeeewww|Stop": -91.59265817853627,
    "eeeeewww|West": -52.88177456285441,
    "eeeefeww|East": -18.16009148509913,
    "eeeefeww|South": -11.605687461699873,
    "eeeefeww|Stop": -81.7003601276189,
    "eeeefeww|West": -13.176689222281494,
    "eeeeffww|East": -12.334731943866712,
    "eeeeffww|South": -2.7599533249278956,
    "eeeeffww|Stop": -1.675836820042495,
    "eeeeffww|West": -9.959095214499696,
    "eeeewwee|East": -113.58974649141678,
    "eeeewwee|North": -27.693646511090193,
    "eeeewwee|Stop": -85.85178459619476,
    "eeeewwee|West": -82.10774229066328,
    "eeeewwef|East": -23.61081499905768,
    "eeeewwef|North": -111.10943319989853,
    "eeeewwef|Stop": -84.91493106960544,
    "eeeewwef|West": -105.37795032211736,
    "eeeewwff|East": -127.83982617224166,
    "eeeewwff|North": -20.749893542941713,
    "eeeewwff|Stop": -123.18141051013869,
    "eeeewwff|West": -154.8034592018112,
    "eeeewwwe|East": -62.735016136972476,
    "eeeewwwe|Stop": -5.067016172592191,
    "eeeewwwe|West": -51.154504804413286,
    "eeeewwwf|East": -106.38018495081484,
    "eeeewwwf|Stop": -85.2563744625127,
    "eeeewwwf|West": -80.90491524025113,
    "eeeewwww|East": -43.496451121347945,
    "eeeewwww|Stop": -114.69743843882212,
    "eeeewwww|West": -122.32482148472371,
    "eeefeeww|East": -101.07550313370974,
    "eeefeeww|South": -2.9560981214487394,
    "eeefeeww|Stop": -98.5152911599957,
    "eeefeeww|West": -2.78127367779874,
    "eeefewwe|East": 0,
    "eeefewwe|Stop": -100.2,
    "eeefewwe|West": -0.2,
    "eeefewww|East": -56.997027000651435,
    "eeefewww|Stop": -146.88203345554328,
    "eeefewww|West": -132.76894584627348,
    "eeeffeww|East": -130.15644664863737,
    "eeeffeww|South": -37.86182407118795,
    "eeeffeww|Stop": -111.47472030477293,
    "eeeffeww|West": -110.23751080444255,
    "eeefffww|East": -6.838176998139501,
    "eeefffww|South": -18.476280747048925,
    "eeefffww|Stop": -81.36786100778747,
    "eeefffww|West": -25.866775615408702,
    "eeefwwee|East": 0,
    "eeefwwee|North": 0,
    "eeefwwee|Stop": 0,
    "eeefwwee|West": -0.26272,
    "eeefwwff|East": 0,
    "eeefwwff|North": 0.7572585202578717,
    "eeefwwff|Stop": 0,
    "eeefwwff|West": 0,
    "eeefwwwe|East": -0.36000000000000004,
    "eeefwwwe|Stop": 0,
    "eeefwwwe|West": 0.2646583575339089,
    "eeefwwwf|East": -100.30530149256789,
    "eeefwwwf|Stop": -102.11838830133411,
    "eeefwwwf|West": -8.244504637093922,
    "eeefwwww|East": 0,
    "eeefwwww|Stop": 0,
    "eeefwwww|West": -2.938493045281138,
    "eeewfeww|East": 0,
    "eeewfeww|South": -0.2,
    "eeewfeww|Stop": 0,
    "eeewfeww|West": 0,
    "eeewweww|East": -137.70086201403342,
    "eeewweww|South": -121.49944661225632,
    "eeewweww|Stop": -140.54887376235249,
    "eeewweww|West": -55.26095917421512,
    "eeewwfww|East": -63.00050095098753,
    "eeewwfww|South": -96.76,
    "eeewwfww|Stop": -104.19285337305492,
    "eeewwfww|West": -80.46248489906307,
    "eeewwwww|East": -0.2,
    "eeewwwww|Stop": 0,
    "eeewwwww|West": 0,
    "eefeewww|East": 1.7424,
    "eefeewww|Stop": 0,
    "eefeewww|West": 0,
    "eefewwee|East": 1.8,
    "eefewwee|North": 0,
    "eefewwee|Stop": -0.2,
    "eefewwee|West": -0.2,
    "eefewwff|East": 1.8,
    "eefewwff|North": 0,
    "eefewwff|Stop": -0.2,
    "eefewwff|West": -0.2,
    "eeffeeww|East": -71.11524888310328,
    "eeffeeww|South": -7.372991018150839,
    "eeffeeww|Stop": -104.06635276488802,
    "eeffeeww|West": -10.330085139367728,
    "eeffefww|East": 0,
    "eeffefww|South": 12.177536372812375,
    "eeffefww|Stop": 0,
    "eeffefww|West": 0,
    "eeffewee|East": 0,
    "eeffewee|North": -0.2,
    "eeffewee|Stop": 0,
    "eeffewee|West": -0.2,
    "eeffewwe|East": -95.60800000000002,
    "eeffewwe|Stop": -0.39200000000000007,
    "eeffewwe|West": -0.488,
    "eeffewww|East": -201.02759836030143,
    "eeffewww|Stop": -203.44920711330738,
    "eeffewww|West": -79.49966372970925,
    "eeffffww|East": -103.77026066468642,
    "eeffffww|South": -89.91632586796516,
    "eeffffww|Stop": -121.683922823261,
    "eeffffww|West": -49.00998544983569,
    "eeffwwff|East": 10.983356655501312,
    "eeffwwff|North": 0,
    "eeffwwff|Stop": -0.2,
    "eeffwwff|West": -0.40608,
    "eeffwwwe|East": 5.6016,
    "eeffwwwe|Stop": -0.2,
    "eeffwwwe|West": -0.2,
    "eeffwwwf|East": -78.94133148642898,
    "eeffwwwf|Stop": -0.39540918272,
    "eeffwwwf|West": -0.27101654449916435,
    "eeffwwww|East": 8.98863525705941,
    "eeffwwww|Stop": -0.2,
    "eeffwwww|West": -0.07199999999999998,
    "eefwweww|East": -6.501701068911544,
    "eefwweww|South": -92.37566589188664,
    "eefwweww|Stop": -71.84659954895855,
    "eefwweww|West": -105.68622533616042,
    "eefwwfww|East": -60.739673945114994,
    "eefwwfww|South": -11.738269008436468,
    "eefwwfww|Stop": -83.57451664726057,
    "eefwwfww|West": -84.06580144900519,
    "eefwwwww|East": 3.9398864623047958,
    "eefwwwww|Stop": -0.2,
    "eefwwwww|West": -0.2,
    "eeweeeww|South": -100.9356661025847,
    "eeweeeww|Stop": -153.53154554095536,
    "eeweeeww|West": -49.73169575749919,
    "eewefeww|South": -0.574239128104741,
    "eewefeww|Stop": -1.3930521050808322,
    "eewefeww|West": -1.7851189856356258,
    "eeweffww|South": 3.7757474349696314,
    "eeweffww|Stop": -160.1359983947769,
    "eeweffww|West": -127.95416257313308,
    "eewfeeee|North": -1.3812809818939984,
    "eewfeeee|South": -4.506105019929859,
    "eewfeeee|Stop": -0.2,
    "eewfeeee|West": -0.23712,
    "eewfeeff|North": 2.450210656343237,
    "eewfeeff|South": 0,
    "eewfeeff|Stop": -0.2,
    "eewfeeff|West": -0.23200000000000004,
    "eewweeew|North": -25.348305143697385,
    "eewweeew|South": -41.63066838599404,
    "eewweeew|Stop": -104.16730174825854,
    "eewweeew|West": -100.913989308416,
    "eewweefw|North": 0,
    "eewweefw|South": 0,
    "eewweefw|Stop": 0,
    "eewweefw|West": -0.4459728033404158,
    "eewwefew|North": -1.296386811050072,
    "eewwefew|South": -89.38152807055275,
    "eewwefew|Stop": -1.1601470771088946,
    "eewwefew|West": -100.66309978654155,
    "eewweffw|North": 7.4456414975461875,
    "eewweffw|South": 0,
    "eewweffw|Stop": 0.4414353245605758,
    "eewweffw|West": -0.2935359262571044,
    "eewwfeew|North": -100.2,
    "eewwfeew|South": -2.4684196897960606,
    "eewwfeew|Stop": -101.84719453185369,
    "eewwfeew|West": -3.748319213469727,
    "eewwfefw|North": -11.090679138358936,
    "eewwfefw|South": 0,
    "eewwfefw|Stop": 0,
    "eewwfefw|West": 0,
    "eewwffew|North": -0.320522752,
    "eewwffew|South": 9.535751434296468,
    "eewwffew|Stop": -0.2,
    "eewwffew|West": -0.29286428104609724,
    "eewwfffw|North": 3.971559477725915,
    "eewwfffw|South": -88.63415070945516,
    "eewwfffw|Stop": -0.2,
    "eewwfffw|West": -8.470082526538112,
    "eewwwwee|North": -0.7833446367988653,
    "eewwwwee|Stop": -0.2,
    "eewwwwee|West": -0.2,
    "eewwwwff|North": 3.1468411123555287,
    "eewwwwff|Stop": 0,
    "eewwwwff|West": 0,
    "efeeewww|East": 0,
    "efeeewww|Stop": 0,
    "efeeewww|West": -10.180020660991305,
    "efefewww|East": -100.78865196116796,
    "efefewww|Stop": -102.05451683622555,
    "efefewww|West": -21.659801150813923,
    "efwweeew|North": -0.32048998400000006,
    "efwweeew|South": 0,
    "efwweeew|Stop": 0,
    "efwweeew|West": 3.992894513083927,
    "efwwefew|North": 0,
    "efwwefew|South": 5.741972464262538,
    "efwwefew|Stop": 0,
    "efwwefew|West": 0,
    "eweeewww|East": -100.2,
    "eweeewww|Stop": 0,
    "ewefeeee|East": -100.2,
    "ewefeeee|North": 0,
    "ewefeeee|South": 0,
    "ewefeeee|Stop": 0,
    "ewefefee|East": -4.538031350496455,
    "ewefefee|North": -2.480350259290271,
    "ewefefee|South": -98.2,
    "ewefefee|Stop": -2.484719197445382,
    "ewewewwe|East": -107.51318297221813,
    "ewewewwe|Stop": -69.4878274227159,
    "ewewewwf|East": -16.77245225090241,
    "ewewewwf|Stop": -104.37763850155342,
    "ewffeeee|East": -96.76,
    "ewffeeee|North": -4.896401970169876,
    "ewffeeee|South": -1.7627223944104602,
    "ewffeeee|Stop": -100.36000000000001,
    "ewffeeww|East": 1.8,
    "ewffeeww|South": 0,
    "ewffeeww|Stop": 0,
    "ewffefee|East": -7.992218194661657,
    "ewffefee|North": -0.2,
    "ewffefee|South": 0.9895738236171625,
    "ewffefee|Stop": -0.2,
    "ewwweeff|North": -0.22922371605856784,
    "ewwweeff|South": -0.9179790844909512,
    "ewwweeff|Stop": -0.39200000000000007,
    "ewwwweee|North": -64.87798691127415,
    "ewwwweee|South": -113.87623841640925,
    "ewwwweee|Stop": -103.68045682591186,
    "ewwwweff|North": 15.563850593131262,
    "ewwwweff|South": -0.23200000000000004,
    "ewwwweff|Stop": -0.2,
    "feeeeeww|East": -1.8136676278200992,
    "feeeeeww|South": -78.059784932309,
    "feeeeeww|Stop": -1.382040814547223,
    "feeeeeww|West": -1.4271750946445168,
    "feeefeww|East": -0.2,
    "feeefeww|South": -0.09206992757428092,
    "feeefeww|Stop": -0.2,
    "feeefeww|West": -0.2,
    "feeewwef|East": -3.467816269791749,
    "feeewwef|North": -99.39827902522214,
    "feeewwef|Stop": -0.35082593558194647,
    "feeewwef|West": 11.840202268788701,
    "feeewwff|East": -8.533854719999999,
    "feeewwff|North": 11.21590501998692,
    "feeewwff|Stop": 0.4412351339614205,
    "feeewwff|West": -96.71625440525574,
    "feeewwwe|East": -12.96962359103398,
    "feeewwwe|Stop": -1.3385854513329147,
    "feeewwwe|West": 0.3105735708292079,
    "feeewwwf|East": 0,
    "feeewwwf|Stop": 2.8265552420021103,
    "feeewwwf|West": 15.233499980656495,
    "feeewwww|East": -0.23712,
    "feeewwww|Stop": -0.2,
    "feeewwww|West": 20.256951003775846,
    "feefeeww|East": -0.054388132716304494,
    "feefeeww|South": 0,
    "feefeeww|Stop": 0,
    "feefeeww|West": -0.2,
    "feefewww|East": 1.4844798166602617,
    "feefewww|Stop": 0,
    "feefewww|West": 0,
    "feefwwwf|East": 0,
    "feefwwwf|Stop": -0.2,
    "feefwwwf|West": 21.969974836488685,
    "feewewww|East": -0.488,
    "feewewww|Stop": -0.39200000000000007,
    "feewewww|West": -0.44320000000000004,
    "feewweww|East": 0,
    "feewweww|South": 1.271602753536,
    "feewweww|Stop": 0,
    "feewweww|West": 0,
    "feewwfww|East": 0,
    "feewwfww|South": 0,
    "feewwfww|Stop": 0,
    "feewwfww|West": -0.2,
    "fefewwee|East": 0,
    "fefewwee|North": 0,
    "fefewwee|Stop": -0.2,
    "fefewwee|West": -0.2,
    "feffeeww|East": -64.74377924026331,
    "feffeeww|South": -95.7822090483363,
    "feffeeww|Stop": -0.8503354982412946,
    "feffeeww|West": -0.9131566218222544,
    "feffwwwf|East": 0,
    "feffwwwf|Stop": 0,
    "feffwwwf|West": 25.488267092735274,
    "fefwwfww|East": -14.404635363131678,
    "fefwwfww|South": 0,
    "fefwwfww|Stop": 0,
    "fefwwfww|West": 0,
    "feweeeww|South": -54.664375301345174,
    "feweeeww|Stop": -102.89867403766776,
    "feweeeww|West": -100.28127020440314,
    "feweffww|South": 10.53612803991156,
    "feweffww|Stop": -0.2,
    "feweffww|West": -0.025643194810588132,
    "fewweeew|North": -11.092875060269035,
    "fewweeew|South": -0.2,
    "fewweeew|Stop": -0.2,
    "fewweeew|West": -0.3033937682432,
    "fewwefew|North": -0.2748478256209482,
    "fewwefew|South": -98.2,
    "fewwefew|Stop": -0.2,
    "fewwefew|West": -0.3169731543664913,
    "fewwfeew|North": -11.561638302731659,
    "fewwfeew|South": -1.192495670542236,
    "fewwfeew|Stop": -1.08621105152,
    "fewwfeew|West": -1.113075696882293,
    "fewwffew|North": -0.25355978202618523,
    "fewwffew|South": 9.216993645792908,
    "fewwffew|Stop": 0.007346073600000086,
    "fewwffew|West": -0.004048974136060313,
    "fewwfffw|North": 0,
    "fewwfffw|South": 0,
    "fewwfffw|Stop": -0.36000000000000004,
    "fewwfffw|West": 5.461982057975543,
    "ffeeeeww|East": 0,
    "ffeeeeww|South": 0,
    "ffeeeeww|Stop": -0.2,
    "ffeeeeww|West": 1.6262062317568,
    "ffeeewee|East": 0,
    "ffeeewee|North": 0,
    "ffeeewee|Stop": -0.2,
    "ffeeewee|West": 3.5279999999999996,
    "ffeeewwe|East": -0.5456000000000001,
    "ffeeewwe|Stop": -0.39200000000000007,
    "ffeeewwe|West": -96.76,
    "ffeeewww|East": -1.5169074339354962,
    "ffeeewww|Stop": -1.3930521050808322,
    "ffeeewww|West": -3.2689597499039746,
    "ffeefeww|East": 0,
    "ffeefeww|South": -0.2,
    "ffeefeww|Stop": 0,
    "ffeefeww|West": 4.5018772479999996,
    "ffeeffww|East": -0.30168320000000004,
    "ffeeffww|South": 14.58877016703426,
    "ffeeffww|Stop": 0,
    "ffeeffww|West": 0,
    "ffeewwee|East": -0.2,
    "ffeewwee|North": 0,
    "ffeewwee|Stop": -0.2,
    "ffeewwee|West": 24.82723695639849,
    "ffeewwef|East": 0,
    "ffeewwef|North": 4.272783070482802,
    "ffeewwef|Stop": 8.014806559746562,
    "ffeewwef|West": 32.95478707857099,
    "ffeewwff|East": -10.08215207537976,
    "ffeewwff|North": 4.832005756674493,
    "ffeewwff|Stop": -11.292706404388959,
    "ffeewwff|West": 28.057959715070655,
    "ffeewwwe|East": -48.553450768291434,
    "ffeewwwe|Stop": -21.205773368316848,
    "ffeewwwe|West": 17.760448019265468,
    "ffeewwwf|East": 12.172265023565654,
    "ffeewwwf|Stop": 16.643265959459622,
    "ffeewwwf|West": 30.97740456739623,
    "ffeewwww|East": 5.262438121340251,
    "ffeewwww|Stop": 18.84685407000376,
    "ffeewwww|West": 32.08625620265135,
    "ffefewww|East": -93.47411887536195,
    "ffefewww|Stop": -78.82738319573322,
    "ffefewww|West": 13.734701230219974,
    "ffefffww|East": 0,
    "ffefffww|South": 3.6915839999999998,
    "ffefffww|Stop": 0,
    "ffefffww|West": 0,
    "ffefwwwe|East": -0.2,
    "ffefwwwe|Stop": 0,
    "ffefwwwe|West": 4.4311679999999996,
    "ffefwwwf|East": 18.683571204949363,
    "ffefwwwf|Stop": 22.53197348250603,
    "ffefwwwf|West": 33.4627492226874,
    "ffewewww|East": 0,
    "ffewewww|Stop": -0.2,
    "ffewewww|West": 3.24,
    "ffewweww|East": -0.4423895996508378,
    "ffewweww|South": -8.736644138268717,
    "ffewweww|Stop": -100.488,
    "ffewweww|West": -86.65480601186178,
    "fffewwee|East": 0,
    "fffewwee|North": 0,
    "fffewwee|Stop": 0,
    "fffewwee|West": 3.6183167999999997,
    "ffffeeww|East": 1.8,
    "ffffeeww|South": 0.8822319932657452,
    "ffffeeww|Stop": -0.2,
    "ffffeeww|West": -0.3106943738379133,
    "ffffwwwf|East": 25.661132998828762,
    "ffffwwwf|Stop": 26.023512977435107,
    "ffffwwwf|West": 35.66976951535426,
    "fffwweww|East": -1.7913215192679548,
    "fffwweww|South": 0,
    "fffwweww|Stop": 0,
    "fffwweww|West": 3.6183167999999997,
    "ffwfeeff|North": 0,
    "ffwfeeff|South": -0.2,
    "ffwfeeff|Stop": 0,
    "ffwfeeff|West": 3.5279999999999996,
    "ffwweefw|North": 0,
    "ffwweefw|South": -0.2,
    "ffwweefw|Stop": 0,
    "ffwweefw|West": 21.114802566701936,
    "ffwweeww|South": 0,
    "ffwweeww|Stop": -100.2,
    "ffwweeww|West": 0,
    "fweeeeef|East": -0.2,
    "fweeeeef|North": -0.2,
    "fweeeeef|South": 0,
    "fweeeeef|Stop": -0.2,
    "fweeefef|East": 0,
    "fweeefef|North": 0,
    "fweeefef|South": 1.4566200737044106,
    "fweeefef|Stop": 0,
    "fwefeeef|East": 0,
    "fwefeeef|North": -0.2,
    "fwefeeef|South": 0,
    "fwefeeef|Stop": 0,
    "fwefefee|East": -0.5025737359934873,
    "fwefefee|North": -0.488,
    "fwefefee|South": -1.0317935469654027,
    "fwefefee|Stop": -0.39200000000000007,
    "fwefefef|East": -0.23200000000000004,
    "fwefefef|North": 0,
    "fwefefef|South": 0,
    "fwefefef|Stop": -0.2,
    "fwewewwf|East": -49.3674929469816,
    "fwewewwf|Stop": -104.19945536666923,
    "fwewfwwe|East": -4.127763827808074,
    "fwewfwwe|Stop": -4.121103846892762,
    "fwewfwwf|East": 20.952417177070544,
    "fwewfwwf|Stop": -104.16412946077259,
    "fwffeeee|East": 0,
    "fwffeeee|North": 0,
    "fwffeeee|South": -0.42288833681293314,
    "fwffeeee|Stop": 0,
    "fwffeeef|East": 5.444928,
    "fwffeeef|North": 0,
    "fwffeeef|South": 0,
    "fwffeeef|Stop": 0,
    "fwffeeff|East": 0,
    "fwffeeff|North": 23.098497885032817,
    "fwffeeff|South": -0.2,
    "fwffeeff|Stop": -0.2,
    "fwffefee|East": -92.70557511202958,
    "fwffefee|North": -101.14017210024943,
    "fwffefee|South": -2.0434359274586447,
    "fwffefee|Stop": -1.2427626094592001,
    "fwffefef|East": 7.001272832,
    "fwffefef|North": -0.2,
    "fwffefef|South": -93.4139938555849,
    "fwffefef|Stop": 0.8466545664000003,
    "fwwwweee|North": -79.73920000000001,
    "fwwwweee|South": -21.61899583549168,
    "fwwwweee|Stop": -81.35219789468418,
    "fwwwweef|North": -0.2,
    "fwwwweef|South": 0,
    "fwwwweef|Stop": 0,
    "fwwwweff|North": -44.087224675854436,
    "fwwwweff|South": 5.957795795593481,
    "fwwwweff|Stop": -99.77916847046119,
    "weeeeeww|East": 0,
    "weeeeeww|South": 0,
    "weeeeeww|Stop": -0.2,
    "weeeeeww|West": -0.2,
    "weeeewww|East": -0.2,
    "weeeewww|Stop": -0.2,
    "weeeewww|West": -0.2,
    "weeewwww|East": -101.98802343027356,
    "weeewwww|Stop": -168.97248848977304,
    "weeewwww|West": -122.17526363410519,
    "weefewww|East": -0.2,
    "weefewww|Stop": -0.2,
    "weefewww|West": -0.36000000000000004,
    "weefwwww|East": -169.39688462660172,
    "weefwwww|Stop": -157.55471384532774,
    "weefwwww|West": -83.08390436489383,
    "weewwwew|East": -100.6643214052305,
    "weewwwew|North": -124.86729947468015,
    "weewwwew|Stop": -101.42986401670208,
    "weewwwew|West": -69.60751469497968,
    "wefewwww|East": -1.9331015949869692,
    "wefewwww|Stop": -0.2,
    "wefewwww|West": -0.2,
    "weffewww|East": -93.0219904,
    "weffewww|Stop": -105.86396988555761,
    "weffewww|West": -82.29292319251829,
    "weffwfww|East": 0,
    "weffwfww|South": -1.6107676176641896,
    "weffwfww|Stop": 0,
    "weffwfww|West": 0,
    "weffwwww|East": -148.0918726913399,
    "weffwwww|Stop": -142.85632548462917,
    "weffwwww|West": -136.16520822236058,
    "wefwwwew|East": -168.4989961969049,
    "wefwwwew|North": -112.02451341090013,
    "wefwwwew|Stop": -148.2976137866163,
    "wefwwwew|West": -16.12937623806595,
    "wefwwwfw|East": -98.2,
    "wefwwwfw|North": -12.927328347064789,
    "wefwwwfw|Stop": -102.68727825653367,
    "wefwwwfw|West": -101.16489028548843,
    "weweeeee|North": -37.81642911339328,
    "weweeeee|South": -95.68033962525755,
    "weweeeee|Stop": 3.83571084366053,
    "weweeeee|West": -8.103043303120085,
    "weweffee|North": 2.781184293455442,
    "weweffee|South": -95.3776,
    "weweffee|Stop": -0.2,
    "weweffee|West": -0.2,
    "wewfeeee|North": -43.50231142524549,
    "wewfeeee|South": -53.90653587590984,
    "wewfeeee|Stop": -47.24011671689105,
    "wewfeeee|West": -9.128999105812102,
    "wewfeeef|North": 23.44732512094707,
    "wewfeeef|South": -0.36773223558624646,
    "wewfeeef|Stop": -0.2,
    "wewfeeef|West": -0.05926622069242389,
    "wewfeeff|North": 21.493384407632842,
    "wewfeeff|South": -69.29975973382474,
    "wewfeeff|Stop": -38.15029932041837,
    "wewfeeff|West": -24.965415674718514,
    "wewfefee|North": -64.33404085176367,
    "wewfefee|South": -26.337768917917604,
    "wewfefee|Stop": -90.85623363277705,
    "wewfefee|West": -42.9672906112964,
    "wewwwfew|North": -0.2,
    "wewwwfew|South": 0,
    "wewwwfew|Stop": 0,
    "wewwwfew|West": -0.2,
    "wfeewwww|East": -52.54559193792917,
    "wfeewwww|Stop": -83.65246406062569,
    "wfeewwww|West": 11.486739570068808,
    "wfewwwew|East": -1.1073300481481492,
    "wfewwwew|North": -2.4761934808601755,
    "wfewwwew|Stop": -1.2427626094592001,
    "wfewwwew|West": -2.766812660136565,
    "wfewwwfw|East": 0,
    "wfewwwfw|North": 16.246654042333425,
    "wfewwwfw|Stop": 0,
    "wfewwwfw|West": 0,
    "wffwwwew|East": -69.83970842541049,
    "wffwwwew|North": -21.143085114017975,
    "wffwwwew|Stop": -89.30092205529927,
    "wffwwwew|West": -98.17946372110555,
    "wweeeeew|East": -6.3193544299178255,
    "wweeeeew|North": -101.45907485244948,
    "wweeeeew|South": -1.6678264033023615,
    "wweeeeew|Stop": -101.42986401670208,
    "wweeeeww|East": -180.29924866561123,
    "wweeeeww|South": -79.0678206724187,
    "wweeeeww|Stop": -173.2173437824756,
    "wweeefew|East": 0,
    "wweeefew|North": 0,
    "wweeefew|South": 1.003368865694546,
    "wweeefew|Stop": 0,
    "wweeeffw|East": -13.085958251738973,
    "wweeeffw|North": 0,
    "wweeeffw|South": 0,
    "wweeeffw|Stop": 0,
    "wweeefww|East": -29.025706082578186,
    "wweeefww|South": -22.830168868758868,
    "wweeefww|Stop": -103.41853539377873,
    "wweefeew|East": -1.0420093335092875,
    "wweefeew|North": -100.2,
    "wweefeew|South": -74.17491426521202,
    "wweefeew|Stop": -0.923136512,
    "wweefeww|East": -130.0942139263699,
    "wweefeww|South": -26.018742783244697,
    "wweefeww|Stop": -117.94667657646052,
    "wweeffew|East": -32.191507765088176,
    "wweeffew|North": -110.51461580894677,
    "wweeffew|South": -120.63306702256179,
    "wweeffew|Stop": -103.74874448925216,
    "wweefffw|East": -0.2,
    "wweefffw|North": 5.1868799999999995,
    "wweefffw|South": 0,
    "wweefffw|Stop": -0.2,
    "wweeffww|East": -96.87088068963837,
    "wweeffww|South": 0.10554924278309263,
    "wweeffww|Stop": -101.540669456034,
    "wweewwee|East": -66.12156641967016,
    "wweewwee|North": -112.89530585059907,
    "wweewwee|Stop": -106.77622529812322,
    "wweewwef|East": -94.6727598353462,
    "wweewwef|North": -7.618272480145221,
    "wweewwef|Stop": -77.07141418266797,
    "wweewwff|East": -49.399594471605695,
    "wweewwff|North": 3.7776383355752596,
    "wweewwff|Stop": -39.72701089975051,
    "wwefeeew|East": -80.42665216,
    "wwefeeew|North": -99.75179250907837,
    "wwefeeew|South": -7.75228389418648,
    "wwefeeew|Stop": -101.540669456034,
    "wwefeefw|East": 0,
    "wwefeefw|North": 5.041325792434586,
    "wwefeefw|South": 0,
    "wwefeefw|Stop": 0,
    "wwefeeww|East": -44.96161584872785,
    "wwefeeww|South": -76.2900413544611,
    "wwefeeww|Stop": -88.20382653049293,
    "wweffeew|East": -0.06975532352291867,
    "wweffeew|North": -100.2,
    "wweffeew|South": -6.296373420123901,
    "wweffeew|Stop": -100.2,
    "wwefffew|East": -117.54595976878606,
    "wwefffew|North": -84.4252584483389,
    "wwefffew|South": -67.80272780570185,
    "wwefffew|Stop": -112.3963760874284,
    "wwefwwee|East": -0.2,
    "wwefwwee|North": 0,
    "wwefwwee|Stop": -0.2,
    "wwewweew|East": -0.2,
    "wwewweew|North": -0.2,
    "wwewweew|South": 0,
    "wwewweew|Stop": -0.2,
    "wwfeeeew|East": 1.6047095848960002,
    "wwfeeeew|North": 0,
    "wwfeeeew|South": 0,
    "wwfeeeew|Stop": -0.2,
    "wwffeeew|East": -8.111819754233988,
    "wwffeeew|North": -49.31819992452333,
    "wwffeeew|South": -13.701585845327998,
    "wwffeeew|Stop": -95.03502402483,
    "wwffeefw|East": -119.31814882952001,
    "wwffeefw|North": 16.146827708067836,
    "wwffeefw|South": -155.15372633350938,
    "wwffeefw|Stop": -83.05922407475235,
    "wwffeeww|East": -30.521469512642977,
    "wwffeeww|South": -132.86704338994318,
    "wwffeeww|Stop": -128.73246842434816,
    "wwfffeew|East": 3.481427566578337,
    "wwfffeew|North": 0,
    "wwfffeew|South": 0,
    "wwfffeew|Stop": 0,
    "wwffffew|East": -110.94841075604644,
    "wwffffew|North": -122.50142445018082,
    "wwffffew|South": -35.5800609039357,
    "wwffffew|Stop": -103.61228482627666,
    "wwffwwee|East": -57.720243663758005,
    "wwffwwee|North": -76.70675827213384,
    "wwffwwee|Stop": -102.87143354297461,
    "wwweeeee|North": -79.19096490142488,
    "wwweeeee|South": -170.40582870650542,
    "wwweeeee|Stop": -190.79859264112486,
    "wwweeeef|North": -71.05248574989648,
    "wwweeeef|South": -140.963090836667,
    "wwweeeef|Stop": -172.33716391080452,
    "wwweeeff|North": -11.780354348869995,
    "wwweeeff|South": -64.38832329165581,
    "wwweeeff|Stop": -109.96025298502474,
    "wwweefee|North": -1.2151776465336455,
    "wwweefee|South": -19.35698224202882,
    "wwweefee|Stop": -1.08621105152,
    "wwwefeee|North": -124.16925808806167,
    "wwwefeee|South": -72.01146186745875,
    "wwwefeee|Stop": -113.59875734844861,
    "wwweffee|North": -101.2265672974336,
    "wwweffee|South": -6.7489789879894655,
    "wwweffee|Stop": -101.31444168406468,
    "wwweweee|North": 5.379940084497658,
    "wwweweee|South": -57.287129396657676,
    "wwweweee|Stop": -78.2132233997619,
    "wwweweef|North": -2.3613780875577755,
    "wwweweef|South": -50.62195729040106,
    "wwweweef|Stop": -101.71745934145763,
    "wwwewefe|North": 2.5803856881785867,
    "wwwewefe|South": 0,
    "wwwewefe|Stop": -0.2,
    "wwweweff|North": -89.00731065642148,
    "wwweweff|South": -42.7322571040047,
    "wwweweff|Stop": -101.4625753371219,
    "wwwewfee|North": 0,
    "wwwewfee|South": 3.5279999999999996,
    "wwwewfee|Stop": 0,
    "wwwfweee|North": -46.12576448628597,
    "wwwfweee|South": -127.56810840577306,
    "wwwfweee|Stop": -142.82687001847452,
    "wwwfweef|North": -159.6694086509773,
    "wwwfweef|South": -118.51050790326241,
    "wwwfweef|Stop": -105.76254093536795,
    "wwwfweff|North": -31.674521043282866,
    "wwwfweff|South": -94.08327781094215,
    "wwwfweff|Stop": -68.73645143401573,
    "wwwweeew|North": -177.91308383571115,
    "wwwweeew|South": -163.276679971575,
    "wwwweeew|Stop": -138.9107585185597,
    "wwwweefw|North": -19.583699488808346,
    "wwwweefw|South": -113.49906403306782,
    "wwwweefw|Stop": -109.38361356165268,
    "wwwwefew|North": -111.37539074294513,
    "wwwwefew|South": -57.31264545351173,
    "wwwwefew|Stop": -92.75037974174383,
    "wwwwfeew|North": -1.4294453074118818,
    "wwwwfeew|South": -101.31549420370364,
    "wwwwfeew|Stop": -1.5132837015781377,
    "wwwwffew|North": -140.6310066633269,
    "wwwwffew|South": 7.081043821469555,
    "wwwwffew|Stop": -168.2296570094517,
    "wwwwweee|North": -55.933950428891244,
    "wwwwweee|South": -132.89951974706275,
    "wwwwweee|Stop": -93.71166393445213,
    "wwwwweef|North": -29.250663987345874,
    "wwwwweef|South": -141.37815713219922,
    "wwwwweef|Stop": -121.61365035411544,
    "wwwwweff|North": -4.304278212518429,
    "wwwwweff|South": -51.12163693441067,
    "wwwwweff|Stop": -47.22859630774418,
    "wwwwwfee|North": -32.130445261171744,
    "wwwwwfee|South": -35.77948414917419,
    "wwwwwfee|Stop": -84.63785329897635
}